README.rst
setup.py
stacksim/__init__.py
stacksim/function.py
stacksim/stack.py
stacksim/stackDirective.py
stacksim/stackSession.py
stacksim/stacksim
stacksim.egg-info/PKG-INFO
stacksim.egg-info/SOURCES.txt
stacksim.egg-info/dependency_links.txt
stacksim.egg-info/entry_points.txt
stacksim.egg-info/requires.txt
stacksim.egg-info/top_level.txt
stacksim/conventions/__init__.py
stacksim/conventions/callinConvention.py
stacksim/conventions/cdecl.py
stacksim/data/libc.c
stacksim/templates/stack.html
test/test_session.py