Metadata-Version: 2.1
Name: stacksim
Version: 0.1.3
Summary: Stack Visualization Tool
